[
    {
        "id": 17965225993184256,
        "created_at": 1540672185,
        "text": "I saw some of those in town today",
        "owner": {
            "id": "249135147",
            "is_verified": false,
            "profile_pic_url": "https://scontent-lhr3-1.cdninstagram.com/vp/4f3fd7685aec0deef0e736178d428c20/5E5752EB/t51.2885-19/s150x150/41488496_319088265488582_4034989025742815232_n.jpg?_nc_ht=scontent-lhr3-1.cdninstagram.com",
            "username": "susanna1405"
        },
        "likes_count": 0,
        "answers": []
    }
]