[
    {
        "id": 17996341453029415,
        "created_at": 1541233014,
        "text": "\ud83d\ude18\u2763",
        "owner": {
            "id": "3526149423",
            "is_verified": false,
            "profile_pic_url": "https://scontent-lhr3-1.cdninstagram.com/vp/dddea21c51b600b0049bf8c921d012c1/5E4854A8/t51.2885-19/s150x150/66403125_360943634568945_8862830822508462080_n.jpg?_nc_ht=scontent-lhr3-1.cdninstagram.com",
            "username": "josying317"
        },
        "likes_count": 0,
        "answers": []
    },
    {
        "id": 17996575789036460,
        "created_at": 1540941596,
        "text": "This is really inspring",
        "owner": {
            "id": "6918687861",
            "is_verified": false,
            "profile_pic_url": "https://scontent-lhr3-1.cdninstagram.com/vp/0a73c6a547839c9e60d0385a4cbf178d/5E4D6DD3/t51.2885-19/s150x150/44309782_441517139711176_8046775796339048448_n.jpg?_nc_ht=scontent-lhr3-1.cdninstagram.com",
            "username": "dank_boi12"
        },
        "likes_count": 1,
        "answers": []
    },
    {
        "id": 17994085867029848,
        "created_at": 1540941586,
        "text": "OMG\ud83d\ude0d\ud83d\ude0d If I were to order this how much would it be in Canada?",
        "owner": {
            "id": "6326765876",
            "is_verified": false,
            "profile_pic_url": "https://scontent-lhr3-1.cdninstagram.com/vp/2863a03ba252266bccf6f8349aaefd3d/5E46BD2D/t51.2885-19/s150x150/40295058_263802844472968_4497053281167605760_n.jpg?_nc_ht=scontent-lhr3-1.cdninstagram.com",
            "username": "natalie_martin_97"
        },
        "likes_count": 1,
        "answers": [
            {
                "id": 17964905959146830,
                "created_at": 1540941675,
                "text": "@natalie_martin_97 you mean my hat?",
                "owner": {
                    "id": "31978248",
                    "is_verified": false,
                    "profile_pic_url": "https://scontent-lhr3-1.cdninstagram.com/vp/f934cf4304fe3f2b84f7fb73839ffc32/5E57BA68/t51.2885-19/s150x150/30084348_231735560738305_5996100809975136256_n.jpg?_nc_ht=scontent-lhr3-1.cdninstagram.com",
                    "username": "kan_lucas"
                },
                "likes_count": 0
            }
        ]
    },
    {
        "id": 17993949967007246,
        "created_at": 1540941585,
        "text": "Well, That's really something",
        "owner": {
            "id": "8124043168",
            "is_verified": false,
            "profile_pic_url": "https://scontent-lhr3-1.cdninstagram.com/vp/90dfaf9b1fb4672141fb9841316920bb/5E472D71/t51.2885-19/s150x150/35575534_262672904504189_1021157298149523456_n.jpg?_nc_ht=scontent-lhr3-1.cdninstagram.com",
            "username": "b7bnn"
        },
        "likes_count": 1,
        "answers": []
    },
    {
        "id": 17930436259216518,
        "created_at": 1540941583,
        "text": "Legend \u2014- from my iphone7 plus",
        "owner": {
            "id": "6027944441",
            "is_verified": false,
            "profile_pic_url": "https://scontent-lhr3-1.cdninstagram.com/vp/d5ac68ac128c135812782d9593b091f8/5E5E6FAF/t51.2885-19/26870755_403137476806026_957148090572210176_n.jpg?_nc_ht=scontent-lhr3-1.cdninstagram.com",
            "username": "yazgan.berkant"
        },
        "likes_count": 1,
        "answers": []
    },
    {
        "id": 17980838983108850,
        "created_at": 1540941583,
        "text": "Legend lol",
        "owner": {
            "id": "6027569938",
            "is_verified": false,
            "profile_pic_url": "https://scontent-lhr3-1.cdninstagram.com/vp/250d115d92313a28215f0582d76b13ba/5E3F5194/t51.2885-19/22427535_702875099898882_8691178997075148800_n.jpg?_nc_ht=scontent-lhr3-1.cdninstagram.com",
            "username": "berkant.yazgan"
        },
        "likes_count": 1,
        "answers": []
    },
    {
        "id": 17931769261213405,
        "created_at": 1540941581,
        "text": "\ud83d\ude02 Legend",
        "owner": {
            "id": "6028634489",
            "is_verified": false,
            "profile_pic_url": "https://scontent-lhr3-1.cdninstagram.com/vp/f8f766836c4d46489ce6fc6d47571678/5E522E6F/t51.2885-19/s150x150/21479898_510437095966855_6780586757072093184_a.jpg?_nc_ht=scontent-lhr3-1.cdninstagram.com",
            "username": "bkt.ygn"
        },
        "likes_count": 1,
        "answers": []
    },
    {
        "id": 17965169686158623,
        "created_at": 1540941581,
        "text": "Legend + 1",
        "owner": {
            "id": "6026921870",
            "is_verified": false,
            "profile_pic_url": "https://scontent-lhr3-1.cdninstagram.com/vp/8e9c7fb09b014c638621eff4a5e68ff5/5E488BB7/t51.2885-19/s150x150/22582361_1468860663231305_2406586157245661184_n.jpg?_nc_ht=scontent-lhr3-1.cdninstagram.com",
            "username": "ygn.bkt"
        },
        "likes_count": 1,
        "answers": []
    },
    {
        "id": 17976851230121192,
        "created_at": 1540941581,
        "text": "\ud83d\ude18\ud83d\ude18\ud83d\ude18 Legend",
        "owner": {
            "id": "6222127832",
            "is_verified": false,
            "profile_pic_url": "https://scontent-lhr3-1.cdninstagram.com/vp/5bdf97debef2ae068a815a9d83a73e3e/5E507EB5/t51.2885-19/22499723_1728926617416765_5547802341345853440_n.jpg?_nc_ht=scontent-lhr3-1.cdninstagram.com",
            "username": "berkant_yazgan"
        },
        "likes_count": 1,
        "answers": []
    },
    {
        "id": 17990041453066246,
        "created_at": 1540941581,
        "text": "Legend +1",
        "owner": {
            "id": "6220536409",
            "is_verified": false,
            "profile_pic_url": "https://scontent-lhr3-1.cdninstagram.com/vp/a995a0094c0d55df200e249e5991c3ef/5E5A7BFF/t51.2885-19/22581037_154413061827658_280205616306192384_n.jpg?_nc_ht=scontent-lhr3-1.cdninstagram.com",
            "username": "atlantikgamesde"
        },
        "likes_count": 1,
        "answers": []
    },
    {
        "id": 17920848004233024,
        "created_at": 1540941580,
        "text": "Hey~~ Beautiful place",
        "owner": {
            "id": "8783882484",
            "is_verified": false,
            "profile_pic_url": "https://scontent-lhr3-1.cdninstagram.com/vp/be8355d4295cbed1e3871169006bb738/5E5B437C/t51.2885-19/44417951_1034063253540124_7215827082012524544_n.jpg?_nc_ht=scontent-lhr3-1.cdninstagram.com",
            "username": "vedr32"
        },
        "likes_count": 1,
        "answers": []
    },
    {
        "id": 17978926297105420,
        "created_at": 1540941580,
        "text": "Nice sharing! Its EYES!!!!!",
        "owner": {
            "id": "4845356067",
            "is_verified": false,
            "profile_pic_url": "https://scontent-lhr3-1.cdninstagram.com/vp/b9cf9689983fa3f4cc2e4830177b2974/5E3E90B7/t51.2885-19/s150x150/18723466_453026681697019_2212591705780125696_a.jpg?_nc_ht=scontent-lhr3-1.cdninstagram.com",
            "username": "ivjkd"
        },
        "likes_count": 1,
        "answers": []
    },
    {
        "id": 17982155770100127,
        "created_at": 1540941580,
        "text": "\ud83d\ude18\ud83d\ude18\ud83d\ude18 Beautiful place",
        "owner": {
            "id": "8784414415",
            "is_verified": false,
            "profile_pic_url": "https://scontent-lhr3-1.cdninstagram.com/vp/d4db903a6d856c1f1daabfededb28e73/5E5EE3C5/t51.2885-19/43585510_2227972297475019_7654190118760087552_n.jpg?_nc_ht=scontent-lhr3-1.cdninstagram.com",
            "username": "aqaqaqaah"
        },
        "likes_count": 1,
        "answers": []
    },
    {
        "id": 17993671453015324,
        "created_at": 1540941580,
        "text": "Its EYES!!!!! lol",
        "owner": {
            "id": "8681339241",
            "is_verified": false,
            "profile_pic_url": "https://scontent-lhr3-1.cdninstagram.com/vp/7e645553dffc6f6b9883d2f1c19a1102/5E440177/t51.2885-19/s150x150/42319317_268047550510613_8063087386344554496_n.jpg?_nc_ht=scontent-lhr3-1.cdninstagram.com",
            "username": "iq__a8"
        },
        "likes_count": 1,
        "answers": []
    },
    {
        "id": 17994491092026825,
        "created_at": 1540941580,
        "text": "Beautiful!! Its EYES!!!!!",
        "owner": {
            "id": "7276592693",
            "is_verified": false,
            "profile_pic_url": "https://scontent-lhr3-1.cdninstagram.com/vp/a23dfeb46da54c85cd669317d0a1be4c/5E430F22/t51.2885-19/s150x150/70168149_469001583825057_4377061180636659712_n.jpg?_nc_ht=scontent-lhr3-1.cdninstagram.com",
            "username": "7_27i"
        },
        "likes_count": 1,
        "answers": []
    },
    {
        "id": 17994531268031779,
        "created_at": 1540941580,
        "text": "\ud83d\ude18\ud83d\ude18\ud83d\ude18 Beautiful place",
        "owner": {
            "id": "8786487064",
            "is_verified": false,
            "profile_pic_url": "https://scontent-lhr3-1.cdninstagram.com/vp/5c603ded74b24da948d5a5cd9727d3e8/5E5E6A29/t51.2885-19/44426511_310802112873233_6916400954480787456_n.jpg?_nc_ht=scontent-lhr3-1.cdninstagram.com",
            "username": "ayayayyah"
        },
        "likes_count": 1,
        "answers": []
    },
    {
        "id": 17921675989226035,
        "created_at": 1540941579,
        "text": "Stunning. Absolute in love with this beauty. \ud83d\ude05 +1",
        "owner": {
            "id": "6941474508",
            "is_verified": false,
            "profile_pic_url": "https://scontent-lhr3-1.cdninstagram.com/vp/27950b44e42cd638aad121aba9ca05f1/5E472259/t51.2885-19/s150x150/26227193_141129993226133_5020428018649137152_n.jpg?_nc_ht=scontent-lhr3-1.cdninstagram.com",
            "username": "c.wd_"
        },
        "likes_count": 1,
        "answers": []
    },
    {
        "id": 17966103835176209,
        "created_at": 1540941579,
        "text": "\ud83d\ude18\ud83d\ude18\ud83d\ude18 Stunning. Absolute in love with this beauty. \ud83d\ude05",
        "owner": {
            "id": "8566435388",
            "is_verified": false,
            "profile_pic_url": "https://scontent-lhr3-1.cdninstagram.com/vp/1f4758e9236eb52b1e38577ab11e3e93/5E477AB1/t51.2885-19/41144316_261878254446550_2486316538559201280_n.jpg?_nc_ht=scontent-lhr3-1.cdninstagram.com",
            "username": "allamihaseen"
        },
        "likes_count": 1,
        "answers": []
    },
    {
        "id": 17994465052023429,
        "created_at": 1540941577,
        "text": "This look is perfect for the weekend! I mean it!",
        "owner": {
            "id": "6247530722",
            "is_verified": false,
            "profile_pic_url": "https://scontent-lhr3-1.cdninstagram.com/vp/dbd6bb88f8b92c19f6b9e6ba16f2994e/5E469FB9/t51.2885-19/51166007_2272087073004172_2358508585392013312_n.jpg?_nc_ht=scontent-lhr3-1.cdninstagram.com",
            "username": "dugunfol"
        },
        "likes_count": 1,
        "answers": []
    },
    {
        "id": 17902763326260094,
        "created_at": 1540941575,
        "text": "Love you\ud83d\ude0d This look is perfect for the weekend!",
        "owner": {
            "id": "6248300588",
            "is_verified": false,
            "profile_pic_url": "https://scontent-lhr3-1.cdninstagram.com/vp/d02ef2d54f14332784e7cf32cf667801/5E57ADF9/t51.2885-19/22582068_1898852883775809_8158009088458883072_n.jpg?_nc_ht=scontent-lhr3-1.cdninstagram.com",
            "username": "ceyizfol"
        },
        "likes_count": 1,
        "answers": []
    },
    {
        "id": 17968967737138631,
        "created_at": 1540941575,
        "text": "Oops, This look is perfect for the weekend!",
        "owner": {
            "id": "4571464912",
            "is_verified": false,
            "profile_pic_url": "https://scontent-lhr3-1.cdninstagram.com/vp/91c6dfe204c1a2b6bc10d2284e7d2a62/5E3F1552/t51.2885-19/s150x150/61611110_334427733894023_3520426255482617856_n.jpg?_nc_ht=scontent-lhr3-1.cdninstagram.com",
            "username": "makeupartists.de"
        },
        "likes_count": 1,
        "answers": []
    },
    {
        "id": 17972806924092313,
        "created_at": 1540941575,
        "text": "\ud83d\udc95\ud83d\udc95 Just fantastic! Thanks for sharing.",
        "owner": {
            "id": "999787765",
            "is_verified": false,
            "profile_pic_url": "https://scontent-lhr3-1.cdninstagram.com/vp/c9171b298816b00040d07e2cf6f04be3/5E4DF974/t51.2885-19/s150x150/70647611_453000381982199_91712227672850432_n.jpg?_nc_ht=scontent-lhr3-1.cdninstagram.com",
            "username": "ilirmalko"
        },
        "likes_count": 1,
        "answers": []
    },
    {
        "id": 17995467082036374,
        "created_at": 1540941573,
        "text": "Oh dear,  When u see a cute boy",
        "owner": {
            "id": "394868234",
            "is_verified": false,
            "profile_pic_url": "https://scontent-lhr3-1.cdninstagram.com/vp/872e5926b70367fcae28106a16311da8/5E564411/t51.2885-19/s150x150/42401286_308816353279843_1041765148236185600_n.jpg?_nc_ht=scontent-lhr3-1.cdninstagram.com",
            "username": "ru_alex_x3"
        },
        "likes_count": 1,
        "answers": []
    },
    {
        "id": 17997220819008512,
        "created_at": 1540940227,
        "text": "\ud83d\udc96 most \u6382 \u6b50\u7f8e\u4ee3\u8cfc \ud83d\uddfc\u4f4e\u81f3\u534a\u50f9 bags & accessories",
        "owner": {
            "id": "4076932812",
            "is_verified": false,
            "profile_pic_url": "https://scontent-lhr3-1.cdninstagram.com/vp/6f9fbc526ebf9670dad0a5e484583c41/5E454655/t51.2885-19/s150x150/41517306_2372469279646962_4459365437066444800_n.jpg?_nc_ht=scontent-lhr3-1.cdninstagram.com",
            "username": "ggbabyshopping"
        },
        "likes_count": 0,
        "answers": []
    },
    {
        "id": 17921184391236100,
        "created_at": 1540940118,
        "text": "#halloweenmcr #mcrhalloween #mcr #manchester #ilovemcr #hkblogger #ukblogger #hkmodel #ukmodel\n#\u6a21\u7279\u5152 #influencer #\u9999\u6e2f\u6a21\u7279\u5152 #influencers #like4likes #selfie  #igtravel #lifewelltravelled #cute\n#fashionblogger #asian #asianboy #asianguy #hkiger #\u66fc\u57ce #\u66fc\u5fb9\u65af\u7279 #\u82f1\u570b #\u82f1\u570b\u65c5\u904a",
        "owner": {
            "id": "31978248",
            "is_verified": false,
            "profile_pic_url": "https://scontent-lhr3-1.cdninstagram.com/vp/f934cf4304fe3f2b84f7fb73839ffc32/5E57BA68/t51.2885-19/s150x150/30084348_231735560738305_5996100809975136256_n.jpg?_nc_ht=scontent-lhr3-1.cdninstagram.com",
            "username": "kan_lucas"
        },
        "likes_count": 0,
        "answers": []
    }
]